LihongyiJiqiXuexiBijiLeemlNotes/README.md
LihongyiJiqiXuexiBijiLeemlNotes/__init__.py
LihongyiJiqiXuexiBijiLeemlNotes/__main__.py
LihongyiJiqiXuexiBijiLeemlNotes/file.epub
LihongyiJiqiXuexiBijiLeemlNotes/index.html
LihongyiJiqiXuexiBijiLeemlNotes/css/__init__.py
LihongyiJiqiXuexiBijiLeemlNotes/css/annotations.css
LihongyiJiqiXuexiBijiLeemlNotes/css/main.css
LihongyiJiqiXuexiBijiLeemlNotes/css/normalize.css
LihongyiJiqiXuexiBijiLeemlNotes/css/popup.css
LihongyiJiqiXuexiBijiLeemlNotes/font/__init__.py
LihongyiJiqiXuexiBijiLeemlNotes/font/fontello.eot
LihongyiJiqiXuexiBijiLeemlNotes/font/fontello.svg
LihongyiJiqiXuexiBijiLeemlNotes/font/fontello.ttf
LihongyiJiqiXuexiBijiLeemlNotes/font/fontello.woff
LihongyiJiqiXuexiBijiLeemlNotes/img/__init__.py
LihongyiJiqiXuexiBijiLeemlNotes/img/annotator-glyph-sprite.png
LihongyiJiqiXuexiBijiLeemlNotes/img/annotator-icon-sprite.png
LihongyiJiqiXuexiBijiLeemlNotes/img/apple-touch-icon.png
LihongyiJiqiXuexiBijiLeemlNotes/img/cancelfullscreen.png
LihongyiJiqiXuexiBijiLeemlNotes/img/close.png
LihongyiJiqiXuexiBijiLeemlNotes/img/fullscreen.png
LihongyiJiqiXuexiBijiLeemlNotes/img/loader.gif
LihongyiJiqiXuexiBijiLeemlNotes/img/menu-icon.png
LihongyiJiqiXuexiBijiLeemlNotes/img/save.png
LihongyiJiqiXuexiBijiLeemlNotes/img/saved.png
LihongyiJiqiXuexiBijiLeemlNotes/img/settings-s.png
LihongyiJiqiXuexiBijiLeemlNotes/img/settings.png
LihongyiJiqiXuexiBijiLeemlNotes/img/star.png
LihongyiJiqiXuexiBijiLeemlNotes/js/__init__.py
LihongyiJiqiXuexiBijiLeemlNotes/js/epub.js
LihongyiJiqiXuexiBijiLeemlNotes/js/epub.min.js
LihongyiJiqiXuexiBijiLeemlNotes/js/epub.min.map
LihongyiJiqiXuexiBijiLeemlNotes/js/hooks.min.js
LihongyiJiqiXuexiBijiLeemlNotes/js/hooks.min.map
LihongyiJiqiXuexiBijiLeemlNotes/js/reader.js
LihongyiJiqiXuexiBijiLeemlNotes/js/reader.js.map
LihongyiJiqiXuexiBijiLeemlNotes/js/reader.min.js
LihongyiJiqiXuexiBijiLeemlNotes/js/reader.min.map
LihongyiJiqiXuexiBijiLeemlNotes/js/hooks/__init__.py
lihongyi_jiqi_xuexi_biji_leeml_notes-2024.3.5.0.dist-info/METADATA
lihongyi_jiqi_xuexi_biji_leeml_notes-2024.3.5.0.dist-info/WHEEL
lihongyi_jiqi_xuexi_biji_leeml_notes-2024.3.5.0.dist-info/entry_points.txt
lihongyi_jiqi_xuexi_biji_leeml_notes-2024.3.5.0.dist-info/top_level.txt
lihongyi_jiqi_xuexi_biji_leeml_notes-2024.3.5.0.dist-info/RECORD
